score.jsapi-0.4.20-py3.7-nspkg.pth
score/jsapi/__init__.py
score/jsapi/_endpoint.py
score/jsapi/_init.py
score/jsapi/cli.py
score/jsapi/exc2json.py
score/jsapi/tpl/es6/exception.js
score/jsapi/tpl/es6/excformat.js
score/jsapi/tpl/es6/queue.js
score/jsapi/tpl/es6/unified.js
score/jsapi/tpl/es6/endpoint/base.js
score/jsapi/tpl/es6/endpoint/index.js
score/jsapi/tpl/es6/endpoint/url.js
score/jsapi/tpl/umd/endpoint.js
score/jsapi/tpl/umd/exception.js
score/jsapi/tpl/umd/excformat.js
score/jsapi/tpl/umd/queue.js
score/jsapi/tpl/umd/unified.js
score/jsapi/tpl/umd/endpoint/url.js
score.jsapi-0.4.20.dist-info/COPYING.LESSER.txt
score.jsapi-0.4.20.dist-info/METADATA
score.jsapi-0.4.20.dist-info/WHEEL
score.jsapi-0.4.20.dist-info/entry_points.txt
score.jsapi-0.4.20.dist-info/namespace_packages.txt
score.jsapi-0.4.20.dist-info/top_level.txt
score.jsapi-0.4.20.dist-info/RECORD
